openinference/instrumentation/dspy/__init__.py
openinference/instrumentation/dspy/package.py
openinference/instrumentation/dspy/py.typed
openinference/instrumentation/dspy/version.py
openinference_instrumentation_dspy-0.1.33.dist-info/METADATA
openinference_instrumentation_dspy-0.1.33.dist-info/WHEEL
openinference_instrumentation_dspy-0.1.33.dist-info/entry_points.txt
openinference_instrumentation_dspy-0.1.33.dist-info/licenses/LICENSE
openinference_instrumentation_dspy-0.1.33.dist-info/RECORD
